{"is_source_file": false, "format": null, "description": "", "external_files": [], "external_methods": [], "published": [], "classes": [], "methods": [], "calls": [], "search-terms": ["videostream-platform-162654-162664", "README.md"], "state": 2, "file_id": 6, "knowledge_revision": 13, "git_revision": "588a3f539e3c32031dbd31eed916bca4133302d9", "hash": "643ecb7b8ae31001829ff27db9fbf0c5", "format-version": 4, "code-base-name": "youtube_frontend", "filename": "README.md", "revision_history": [{"13": "588a3f539e3c32031dbd31eed916bca4133302d9"}]}